CHANGES.rst
MANIFEST.in
README.rst
setup.cfg
setup.py
anybox/__init__.py
anybox.testing.openerp.egg-info/PKG-INFO
anybox.testing.openerp.egg-info/SOURCES.txt
anybox.testing.openerp.egg-info/dependency_links.txt
anybox.testing.openerp.egg-info/not-zip-safe
anybox.testing.openerp.egg-info/requires.txt
anybox.testing.openerp.egg-info/top_level.txt
anybox/testing/__init__.py
anybox/testing/openerp/__init__.py
anybox/testing/openerp/assertions.py
anybox/testing/openerp/sharedsetup.py
anybox/testing/openerp/transactioncase.py
anybox/testing/openerp/tests/__init__.py
anybox/testing/openerp/tests/test_assertions.py
anybox/testing/openerp/tests/test_shared_setup.py