Metadata-Version: 1.1
Name: anybox.testing.openerp
Version: 1.2
Summary: Useful testing base classes and tools for OpenERP
Home-page: https://bitbucket.org/anybox/anybox.testing.openerp
Author: Anybox
Author-email: contact@anybox.fr
License: AGPL v3+
Platform: UNKNOWN
Classifier: Development Status :: 5 - Production/Stable
Classifier: Intended Audience :: Developers
Classifier: Topic :: Software Development :: Libraries :: Python Modules
